tensorboard_plugin_3d/__init__.py
tensorboard_plugin_3d/demo.py
tensorboard_plugin_3d/plugin.py
tensorboard_plugin_3d/static/index.html
tensorboard_plugin_3d/static/index.js
tensorboard_plugin_3d/static/itk/image-io/BMPImageIOReadImage.js
tensorboard_plugin_3d/static/itk/image-io/BMPImageIOReadImage.umd.js
tensorboard_plugin_3d/static/itk/image-io/BMPImageIOReadImage.wasm
tensorboard_plugin_3d/static/itk/image-io/BMPImageIOWriteImage.js
tensorboard_plugin_3d/static/itk/image-io/BMPImageIOWriteImage.umd.js
tensorboard_plugin_3d/static/itk/image-io/BMPImageIOWriteImage.wasm
tensorboard_plugin_3d/static/itk/image-io/BioRadImageIOReadImage.js
tensorboard_plugin_3d/static/itk/image-io/BioRadImageIOReadImage.umd.js
tensorboard_plugin_3d/static/itk/image-io/BioRadImageIOReadImage.wasm
tensorboard_plugin_3d/static/itk/image-io/BioRadImageIOWriteImage.js
tensorboard_plugin_3d/static/itk/image-io/BioRadImageIOWriteImage.umd.js
tensorboard_plugin_3d/static/itk/image-io/BioRadImageIOWriteImage.wasm
tensorboard_plugin_3d/static/itk/image-io/CompressStringify.js
tensorboard_plugin_3d/static/itk/image-io/CompressStringify.umd.js
tensorboard_plugin_3d/static/itk/image-io/CompressStringify.wasm
tensorboard_plugin_3d/static/itk/image-io/FDFImageIOReadImage.js
tensorboard_plugin_3d/static/itk/image-io/FDFImageIOReadImage.umd.js
tensorboard_plugin_3d/static/itk/image-io/FDFImageIOReadImage.wasm
tensorboard_plugin_3d/static/itk/image-io/FDFImageIOWriteImage.js
tensorboard_plugin_3d/static/itk/image-io/FDFImageIOWriteImage.umd.js
tensorboard_plugin_3d/static/itk/image-io/FDFImageIOWriteImage.wasm
tensorboard_plugin_3d/static/itk/image-io/GDCMImageIOReadImage.js
tensorboard_plugin_3d/static/itk/image-io/GDCMImageIOReadImage.umd.js
tensorboard_plugin_3d/static/itk/image-io/GDCMImageIOReadImage.wasm
tensorboard_plugin_3d/static/itk/image-io/GDCMImageIOWriteImage.js
tensorboard_plugin_3d/static/itk/image-io/GDCMImageIOWriteImage.umd.js
tensorboard_plugin_3d-1.0.3.dist-info/METADATA
tensorboard_plugin_3d-1.0.3.dist-info/WHEEL
tensorboard_plugin_3d-1.0.3.dist-info/entry_points.txt
tensorboard_plugin_3d-1.0.3.dist-info/top_level.txt
tensorboard_plugin_3d-1.0.3.dist-info/RECORD
