Metadata-Version: 2.1
Name: tensorboard-plugin-3d
Version: 1.0.3
Summary: TensorBoard plugin for 3D visualization
Home-page: https://github.com/KitwareMedical/tensorboard-plugin-3d
License: UNKNOWN
Platform: UNKNOWN
Requires-Dist: tensorflow
